{
    "data": [
      {
        "UserId": 374,
        "FullName": "Tejs Broberg"
      },
      {
        "UserId": 2379,
        "FullName": "Benjamin Sauer"
      },
      {
        "UserId": 1837,
        "FullName": "Sam Terry"
      },
      {
        "UserId": 1244,
        "FullName": "Marc Berg"
      },
      {
        "UserId": 1526,
        "FullName": "Demo 004"
      },
      {
        "UserId": 372,
        "FullName": "Ben Jones"
      },
      {
        "UserId": 658,
        "FullName": "Andrew Lau"
      },
      {
        "UserId": 655,
        "FullName": "Paul Ireland"
      },
      {
        "UserId": 1313,
        "FullName": "Demo 001"
      },
      {
        "UserId": 1647,
        "FullName": "Lindsey Ahn 2"
      },
      {
        "UserId": 924,
        "FullName": "Jim Walker"
      },
      {
        "UserId": 377,
        "FullName": "Lindsey Ahn"
      },
      {
        "UserId": 376,
        "FullName": "Mike Jeun"
      },
      {
        "UserId": 1033,
        "FullName": "Michael Woznica"
      },
      {
        "UserId": 373,
        "FullName": "Christy Cho"
      },
      {
        "UserId": 523,
        "FullName": "Mike Analyst"
      }
    ]
  }
  